vcron/__init__.py
vcron/app.py
vcron/main.py
vcron/vcron.tcss
vcron-0.2.0.dist-info/LICENSE
vcron-0.2.0.dist-info/METADATA
vcron-0.2.0.dist-info/WHEEL
vcron-0.2.0.dist-info/entry_points.txt
vcron-0.2.0.dist-info/RECORD
