Metadata-Version: 2.1
Name: vcron
Version: 0.2.0
Summary: 
Home-page: https://github.com/laixintao/vcron
License: GPLv3
Keywords: python3
Author: laixintao
Author-email: laixintaoo@gmail.com
Requires-Python: >=3.8.1,<4.0.0
Classifier: Development Status :: 4 - Beta
Classifier: Intended Audience :: Developers
Classifier: License :: Other/Proprietary License
Classifier: Operating System :: MacOS
Classifier: Operating System :: POSIX :: Linux
Classifier: Programming Language :: Python :: 3
Classifier: Programming Language :: Python :: 3.9
Classifier: Programming Language :: Python :: 3.10
Classifier: Programming Language :: Python :: 3.11
Classifier: Programming Language :: Python :: 3.12
Classifier: Programming Language :: Python :: 3.8
Classifier: Typing :: Typed
Requires-Dist: click (>=8.1.7,<9.0.0)
Requires-Dist: cron-descriptor (>=1.4.0,<2.0.0)
Requires-Dist: croniter (>=2.0.1,<3.0.0)
Requires-Dist: textual (>=0.45.0,<0.46.0)
Project-URL: Bug Tracker, https://github.com/laixintao/vcron/issues
